setup.py
sq/__init__.py
sq/exc.py
sq/timezone.py
sq.egg-info/PKG-INFO
sq.egg-info/SOURCES.txt
sq.egg-info/dependency_links.txt
sq.egg-info/requires.txt
sq.egg-info/top_level.txt
sq/datastructures/__init__.py
sq/ddd/__init__.py
sq/ddd/aggregate.py
sq/ddd/base.py
sq/ddd/entity.py
sq/ddd/exc.py
sq/ddd/meta.py
sq/ddd/publisher.py
sq/ddd/schema.py
sq/interfaces/__init__.py
sq/interfaces/wsgi/__init__.py
sq/interfaces/wsgi/ctrl.py
sq/interfaces/wsgi/defaults.py
sq/interfaces/wsgi/exc.py
sq/interfaces/wsgi/methods.py
sq/schema/__init__.py