Metadata-Version: 1.0
Name: sq
Version: 1.0a1
Summary: Sovereign Quantum Framework Application Library
Home-page: https://www.wizardsofindustry.net
Author: Cochise Ruhulessin
Author-email: cochiseruhulessin@gmail.com
License: UNKNOWN
Platform: UNKNOWN
